jsonl2html/__init__.py
jsonl2html/config.json
jsonl2html/config.py
jsonl2html/convert.py
jsonl2html/create_table_of_content.py
jsonl2html/html_template.html
jsonl2html/logger.py
jsonl2html-0.3.0.dist-info/licenses/LICENSE
jsonl2html-0.3.0.dist-info/METADATA
jsonl2html-0.3.0.dist-info/WHEEL
jsonl2html-0.3.0.dist-info/entry_points.txt
jsonl2html-0.3.0.dist-info/top_level.txt
jsonl2html-0.3.0.dist-info/RECORD
