Metadata-Version: 2.4
Name: jsonl2html
Version: 0.3.0
Summary: A tool to convert JSONL to HTML
Author-email: Adamenko Pavel <padamenko@gmail.com>
License-Expression: MIT
Project-URL: Homepage, https://github.com/padap/jsonl2html
Project-URL: Bug Tracker, https://github.com/padap/jsonl2html/issues
Classifier: Programming Language :: Python :: 3
Classifier: Programming Language :: Python :: 3.6
Classifier: Programming Language :: Python :: 3.7
Classifier: Programming Language :: Python :: 3.8
Classifier: Programming Language :: Python :: 3.9
Classifier: Programming Language :: Python :: 3.10
Classifier: Programming Language :: Python :: 3.11
Classifier: Programming Language :: Python :: 3.12
Requires-Python: >=3.6
License-File: LICENSE
Provides-Extra: dev
Requires-Dist: black; extra == "dev"
Requires-Dist: flake8; extra == "dev"
Requires-Dist: pylint; extra == "dev"
Requires-Dist: pytest; extra == "dev"
Requires-Dist: fire; extra == "dev"
Requires-Dist: tabulate; extra == "dev"
Requires-Dist: build; extra == "dev"
Requires-Dist: pandas; extra == "dev"
Dynamic: license-file
